AUTHORS.txt
CHANGES.txt
DEPENDENCIES.txt
FAQ.txt
HISTORY.txt
LICENSE.txt
README.txt
VERSION.txt
setup.py
Quadtree.egg-info/PKG-INFO
Quadtree.egg-info/SOURCES.txt
Quadtree.egg-info/dependency_links.txt
Quadtree.egg-info/top_level.txt
quadtree/__init__.py
quadtree/_treemodule.c
shapelib/ChangeLog
shapelib/LICENSE.txt
shapelib/README
shapelib/README.shapelib
shapelib/README.tree
shapelib/shapefil.h
shapelib/shapelib.html
shapelib/shp_api.html
shapelib/shpopen.c
shapelib/shptree.c
tests/QuadTree.txt
tests/benchmarks.py
tests/boxes_15x15.dat
tests/runalltests.py
tests/runtests
