Metadata-Version: 1.0
Name: Quadtree
Version: 0.1.2
Summary: Quadtree spatial index for Python GIS
Home-page: http://icon.stoa.org/trac/pleiades/wiki/QuadTree
Author: Sean Gillies
Author-email: sgillies@frii.com
License: BSD
Keywords: spatial index
Platform: UNKNOWN
Classifier: Development Status :: 3 - Alpha
Classifier: Intended Audience :: Developers
Classifier: Intended Audience :: Science/Research
Classifier: License :: OSI Approved :: BSD License
Classifier: Operating System :: OS Independent
Classifier: Programming Language :: C
Classifier: Programming Language :: Python
Classifier: Topic :: Scientific/Engineering :: GIS
Classifier: Topic :: Database
